ai/backend/account_manager/VERSION
ai/backend/account_manager/__init__.py
ai/backend/account_manager/config.py
ai/backend/account_manager/context.py
ai/backend/account_manager/defs.py
ai/backend/account_manager/exceptions.py
ai/backend/account_manager/plugin.py
ai/backend/account_manager/py.typed
ai/backend/account_manager/server.py
ai/backend/account_manager/types.py
ai/backend/account_manager/utils.py
ai/backend/account_manager/api/__init__.py
ai/backend/account_manager/api/application.py
ai/backend/account_manager/api/auth.py
ai/backend/account_manager/api/utils.py
ai/backend/account_manager/cli/__init__.py
ai/backend/account_manager/cli/__main__.py
ai/backend/account_manager/cli/context.py
ai/backend/account_manager/cli/start_server.py
ai/backend/account_manager/models/__init__.py
ai/backend/account_manager/models/application.py
ai/backend/account_manager/models/base.py
ai/backend/account_manager/models/keypair.py
ai/backend/account_manager/models/user.py
ai/backend/account_manager/models/userprofile.py
ai/backend/account_manager/models/utils.py
ai/backend/account_manager/models/alembic/__init__.py
ai/backend/account_manager/models/alembic/env.py
backend_ai_account_manager-26.1.0.dist-info/METADATA
backend_ai_account_manager-26.1.0.dist-info/WHEEL
backend_ai_account_manager-26.1.0.dist-info/entry_points.txt
backend_ai_account_manager-26.1.0.dist-info/namespace_packages.txt
backend_ai_account_manager-26.1.0.dist-info/top_level.txt
backend_ai_account_manager-26.1.0.dist-info/RECORD
